setup.py
hotswappy/__init__.py
hotswappy/hotswappy.py
hotswappy.egg-info/PKG-INFO
hotswappy.egg-info/SOURCES.txt
hotswappy.egg-info/dependency_links.txt
hotswappy.egg-info/top_level.txt