Metadata-Version: 1.1
Name: hotswappy
Version: 0.0.2
Summary: A plugin hot-loader.
Home-page: https://bitbucket.org/taybird/hotswappy
Author: Tay Frost
Author-email: taylor@taybird.com
License: BSD
Platform: UNKNOWN
Classifier: Development Status :: 3 - Alpha
Classifier: License :: OSI Approved :: BSD License
Classifier: Intended Audience :: Developers
